bentoctl-0.4.0.dist-info/METADATA
bentoctl-0.4.0.dist-info/WHEEL
bentoctl-0.4.0.dist-info/entry_points.txt
bentoctl-0.4.0.dist-info/licenses/LICENSE.md
bentoctl/__init__.py
bentoctl/cli/__init__.py
bentoctl/cli/interactive.py
bentoctl/cli/operator_management.py
bentoctl/cli/utils.py
bentoctl/console.py
bentoctl/deployment_config.py
bentoctl/docker_utils.py
bentoctl/exceptions.py
bentoctl/operator/README.md
bentoctl/operator/__init__.py
bentoctl/operator/constants.py
bentoctl/operator/operator.py
bentoctl/operator/registry.py
bentoctl/operator/utils/__init__.py
bentoctl/operator/utils/github.py
bentoctl/utils/__init__.py
bentoctl/utils/operator_helpers/__init__.py
bentoctl/utils/operator_helpers/create_deployable.py
bentoctl/utils/operator_helpers/generate.py
bentoctl/utils/operator_helpers/utils.py
bentoctl/utils/operator_helpers/values.py
bentoctl/utils/temp_dir.py
bentoctl/utils/terraform.py
bentoctl/utils/usage_stats.py
bentoctl-0.4.0.dist-info/RECORD
