Metadata-Version: 2.1
Name: bentoctl
Version: 0.4.0
Summary: Fast model deployment with BentoML on cloud platforms.
Author-Email: bentoml.org <contact@bentoml.com>
License: Apache-2.0
Classifier: License :: OSI Approved :: Apache Software License
Classifier: Operating System :: OS Independent
Classifier: Programming Language :: Python :: 3.8
Classifier: Programming Language :: Python :: 3.9
Classifier: Programming Language :: Python :: 3.10
Classifier: Programming Language :: Python :: 3.11
Classifier: Topic :: Software Development
Project-URL: Source, https://github.com/bentoml/bentoctl
Project-URL: User slack community, http://join.slack.bentoml.org
Project-URL: Bug reports, https://github.com/bentoml/bentoctl/issues
Project-URL: Homepage, https://github.com/bentoml/bentoctl
Requires-Python: <4.0,>=3.8
Requires-Dist: bentoml<2,>=1.0.24
Requires-Dist: click>=8
Requires-Dist: cerberus<2,>=1
Requires-Dist: rich==12.*
Requires-Dist: PYYAML>=6
Requires-Dist: simple-term-menu==0.4.4
Requires-Dist: docker>=5
Requires-Dist: semantic-version<3.0.0,>=2.9.0
